mlsdk
